nlu/__init__.py
nlu/component_resolution.py
nlu/discovery.py
nlu/info.py
nlu/namespace.py
nlu/pipe_components.py
nlu/pipeline.py
nlu/pipeline_logic.py
nlu/components/__init__.py
nlu/components/chunker.py
nlu/components/classifier.py
nlu/components/embedding.py
nlu/components/embeddings_chunker.py
nlu/components/labeled_dependency_parser.py
nlu/components/lemmatizer.py
nlu/components/matcher.py
nlu/components/normalizer.py
nlu/components/sentence_detector.py
nlu/components/sequence2sequence.py
nlu/components/spell_checker.py
nlu/components/stemmer.py
nlu/components/stopwordscleaner.py
nlu/components/tokenizer.py
nlu/components/unlabeled_dependency_parser.py
nlu/components/util.py
nlu/components/chunkers/__init__.py
nlu/components/chunkers/default_chunker/__init__.py
nlu/components/chunkers/default_chunker/component_infos.json
nlu/components/chunkers/default_chunker/default_chunker.py
nlu/components/chunkers/ngram/__init__.py
nlu/components/chunkers/ngram/component_infos.json
nlu/components/chunkers/ngram/ngram.py
nlu/components/classifiers/__init__.py
nlu/components/classifiers/classifier_dl/__init__.py
nlu/components/classifiers/classifier_dl/classifier_dl.py
nlu/components/classifiers/classifier_dl/component_infos.json
nlu/components/classifiers/language_detector/__init__.py
nlu/components/classifiers/language_detector/component_infos.json
nlu/components/classifiers/language_detector/language_detector.py
nlu/components/classifiers/multi_classifier/__init__.py
nlu/components/classifiers/multi_classifier/component_infos.json
nlu/components/classifiers/multi_classifier/multi_classifier.py
nlu/components/classifiers/named_entity_recognizer_crf/__init__.py
nlu/components/classifiers/named_entity_recognizer_crf/component_infos.json
nlu/components/classifiers/named_entity_recognizer_crf/ner_crf.py
nlu/components/classifiers/ner/__init__.py
nlu/components/classifiers/ner/component_infos.json
nlu/components/classifiers/ner/ner_dl.py
nlu_spark23-1.1.1rc2.dist-info/LICENSE
nlu_spark23-1.1.1rc2.dist-info/METADATA
nlu_spark23-1.1.1rc2.dist-info/WHEEL
nlu_spark23-1.1.1rc2.dist-info/top_level.txt
nlu_spark23-1.1.1rc2.dist-info/RECORD
