Metadata-Version: 2.1
Name: nlu-spark23
Version: 1.1.1rc2
Summary: John Snow Labs NLU provides state of the art algorithms for NLP&NLU with hundreds of pretrained models in 60+ languages. It enables swift and simple development and research with its powerful Pythonic and Keras inspired API. It is powerd by John Snow Labs powerful Spark NLP library.
Home-page: http://nlu.johnsnowlabs.com
Author: John Snow Labs
Author-email: christian@johnsnowlabs.com
License: UNKNOWN
Keywords: NLP spark development NLU
Platform: UNKNOWN
Classifier: Development Status :: 5 - Production/Stable
Classifier: Intended Audience :: Developers
Classifier: Topic :: Software Development :: Build Tools
Classifier: License :: OSI Approved :: Apache Software License
Classifier: Programming Language :: Python :: 2
Classifier: Programming Language :: Python :: 2.7
Classifier: Programming Language :: Python :: 3
Classifier: Programming Language :: Python :: 3.4
Classifier: Programming Language :: Python :: 3.5
Classifier: Programming Language :: Python :: 3.6
Requires-Dist: spark-nlp (<2.8,>=2.7.1)
Requires-Dist: numpy
Requires-Dist: pyarrow (>=0.16.0)
Requires-Dist: pandas
Requires-Dist: dataclasses
